BayesNetCreacion/__init__.py
BayesNetCreacion/bayesnetc.py
BayesNetCreacion/test.py
BayesNetCreacion/testing.py
BayesNetCreacion-1.2.0.dist-info/METADATA
BayesNetCreacion-1.2.0.dist-info/WHEEL
BayesNetCreacion-1.2.0.dist-info/top_level.txt
BayesNetCreacion-1.2.0.dist-info/RECORD
