Metadata-Version: 2.1
Name: BayesNetCreacion
Version: 1.2.0
Summary: Library capable of creating Bayesian Networks and making probabilistic inference over them, as well additional functions
Author: Andres de la Roca
Author-email: <dela20332@uvg.edu.gt>
Keywords: python,bayes,bayesian network,zero dependencies,bayesian inference,python3,open source
Classifier: Intended Audience :: Developers
Classifier: Programming Language :: Python :: 3
Classifier: Operating System :: Microsoft :: Windows
